[
  {
    "changeuuid": "61763e16-8751-4001-be93-deb44f1a53bd",
    "stationuuid": "6bbf82e2-d201-49f8-886b-56ddc1c7024e",
    "serveruuid": "7dc31a18-85ba-4582-9b3a-a377c2e58ed8",
    "name": "playlist.m3u8",
    "url": "https://live.creacast.com/grandlilletv/smil:grandlilletv.smil/playlist.m3u8",
    "url_resolved": "https://live.creacast.com/grandlilletv/smil:grandlilletv.smil/playlist.m3u8",
    "homepage": "",
    "favicon": "",
    "tags": "",
    "country": "",
    "countrycode": "",
    "iso_3166_2": "",
    "state": "",
    "language": "",
    "languagecodes": "",
    "votes": 0,
    "lastchangetime": "2025-10-24 04:13:18",
    "lastchangetime_iso8601": "2025-10-24T04:13:18Z",
    "codec": "MP3",
    "bitrate": 128,
    "hls": 1,
    "lastcheckok": 1,
    "lastchecktime": "2025-10-24 04:13:18",
    "lastchecktime_iso8601": "2025-10-24T04:13:18Z",
    "lastcheckoktime": "2025-10-24 04:13:18",
    "lastcheckoktime_iso8601": "2025-10-24T04:13:18Z",
    "lastlocalchecktime": "2025-10-24 04:13:18",
    "lastlocalchecktime_iso8601": "2025-10-24T04:13:18Z",
    "clicktimestamp": "2025-10-24 04:13:18",
    "clicktimestamp_iso8601": "2025-10-24T04:13:18Z",
    "clickcount": 0,
    "clicktrend": 0,
    "ssl_error": 0,
    "geo_lat": null,
    "geo_long": null,
    "geo_distance": null,
    "has_extended_info": false
  },
  {
    "changeuuid": "2261dd16-1551-42d6-a4a1-c8243081a362",
    "stationuuid": "5f6e299f-8257-448a-a91b-93cb174e1d53",
    "serveruuid": "ece68e16-d0ed-48b6-a1fb-9e15ac39c034",
    "name": "info.m3u8",
    "url": "https://raw.githubusercontent.com/naveenland4/News_Channels/main/assets/info.m3u8",
    "url_resolved": "https://raw.githubusercontent.com/naveenland4/News_Channels/main/assets/info.m3u8",
    "homepage": "",
    "favicon": "",
    "tags": "",
    "country": "",
    "countrycode": "",
    "iso_3166_2": "",
    "state": "",
    "language": "",
    "languagecodes": "",
    "votes": 0,
    "lastchangetime": "2025-10-24 04:13:18",
    "lastchangetime_iso8601": "2025-10-24T04:13:18Z",
    "codec": "MP3",
    "bitrate": 128,
    "hls": 1,
    "lastcheckok": 1,
    "lastchecktime": "2025-10-24 04:13:18",
    "lastchecktime_iso8601": "2025-10-24T04:13:18Z",
    "lastcheckoktime": "2025-10-24 04:13:18",
    "lastcheckoktime_iso8601": "2025-10-24T04:13:18Z",
    "lastlocalchecktime": "2025-10-24 04:13:18",
    "lastlocalchecktime_iso8601": "2025-10-24T04:13:18Z",
    "clicktimestamp": "2025-10-24 04:13:18",
    "clicktimestamp_iso8601": "2025-10-24T04:13:18Z",
    "clickcount": 0,
    "clicktrend": 0,
    "ssl_error": 0,
    "geo_lat": null,
    "geo_long": null,
    "geo_distance": null,
    "has_extended_info": false
  },
  {
    "changeuuid": "936a42f2-bb06-44f9-b30a-fffd89446003",
    "stationuuid": "9b68abea-5311-469d-bfa1-d80e1ef26b8b",
    "serveruuid": "1ba99981-5bf3-444d-8abc-c95e6fb84770",
    "name": "info.m3u8",
    "url": "https://raw.githubusercontent.com/naveenland4/UTLive/main/assets/info.m3u8",
    "url_resolved": "https://raw.githubusercontent.com/naveenland4/UTLive/main/assets/info.m3u8",
    "homepage": "",
    "favicon": "",
    "tags": "",
    "country": "",
    "countrycode": "",
    "iso_3166_2": "",
    "state": "",
    "language": "",
    "languagecodes": "",
    "votes": 0,
    "lastchangetime": "2025-10-24 04:13:18",
    "lastchangetime_iso8601": "2025-10-24T04:13:18Z",
    "codec": "MP3",
    "bitrate": 128,
    "hls": 1,
    "lastcheckok": 1,
    "lastchecktime": "2025-10-24 04:13:18",
    "lastchecktime_iso8601": "2025-10-24T04:13:18Z",
    "lastcheckoktime": "2025-10-24 04:13:18",
    "lastcheckoktime_iso8601": "2025-10-24T04:13:18Z",
    "lastlocalchecktime": "2025-10-24 04:13:18",
    "lastlocalchecktime_iso8601": "2025-10-24T04:13:18Z",
    "clicktimestamp": "2025-10-24 04:13:18",
    "clicktimestamp_iso8601": "2025-10-24T04:13:18Z",
    "clickcount": 0,
    "clicktrend": 0,
    "ssl_error": 0,
    "geo_lat": null,
    "geo_long": null,
    "geo_distance": null,
    "has_extended_info": false
  }
]