[
  {
    "changeuuid": "2b60ed2e-2cbd-4558-862d-53fa055529bc",
    "stationuuid": "973f689f-fb08-4896-834f-99ea95dd4f42",
    "serveruuid": "0d540f8d-cad9-4e94-bc40-a35eb499cd01",
    "name": "playlist.m3u8",
    "url": "https://live.creacast.com/grandlilletv/smil:grandlilletv.smil/playlist.m3u8",
    "url_resolved": "https://live.creacast.com/grandlilletv/smil:grandlilletv.smil/playlist.m3u8",
    "homepage": "",
    "favicon": "",
    "tags": "",
    "country": "",
    "countrycode": "",
    "iso_3166_2": "",
    "state": "",
    "language": "",
    "languagecodes": "",
    "votes": 0,
    "lastchangetime": "2025-10-23 21:32:08",
    "lastchangetime_iso8601": "2025-10-23T21:32:08Z",
    "codec": "MP3",
    "bitrate": 128,
    "hls": 1,
    "lastcheckok": 1,
    "lastchecktime": "2025-10-23 21:32:08",
    "lastchecktime_iso8601": "2025-10-23T21:32:08Z",
    "lastcheckoktime": "2025-10-23 21:32:08",
    "lastcheckoktime_iso8601": "2025-10-23T21:32:08Z",
    "lastlocalchecktime": "2025-10-23 21:32:08",
    "lastlocalchecktime_iso8601": "2025-10-23T21:32:08Z",
    "clicktimestamp": "2025-10-23 21:32:08",
    "clicktimestamp_iso8601": "2025-10-23T21:32:08Z",
    "clickcount": 0,
    "clicktrend": 0,
    "ssl_error": 0,
    "geo_lat": null,
    "geo_long": null,
    "geo_distance": null,
    "has_extended_info": false
  },
  {
    "changeuuid": "8f4d81fd-3174-4a60-b4cd-ae09295fe611",
    "stationuuid": "77799f1f-20e8-4804-967e-c518dda19664",
    "serveruuid": "c3fb96e6-af56-409a-b067-327d5d7ecc39",
    "name": "info.m3u8",
    "url": "https://raw.githubusercontent.com/naveenland4/News_Channels/main/assets/info.m3u8",
    "url_resolved": "https://raw.githubusercontent.com/naveenland4/News_Channels/main/assets/info.m3u8",
    "homepage": "",
    "favicon": "",
    "tags": "",
    "country": "",
    "countrycode": "",
    "iso_3166_2": "",
    "state": "",
    "language": "",
    "languagecodes": "",
    "votes": 0,
    "lastchangetime": "2025-10-23 21:32:08",
    "lastchangetime_iso8601": "2025-10-23T21:32:08Z",
    "codec": "MP3",
    "bitrate": 128,
    "hls": 1,
    "lastcheckok": 1,
    "lastchecktime": "2025-10-23 21:32:08",
    "lastchecktime_iso8601": "2025-10-23T21:32:08Z",
    "lastcheckoktime": "2025-10-23 21:32:08",
    "lastcheckoktime_iso8601": "2025-10-23T21:32:08Z",
    "lastlocalchecktime": "2025-10-23 21:32:08",
    "lastlocalchecktime_iso8601": "2025-10-23T21:32:08Z",
    "clicktimestamp": "2025-10-23 21:32:08",
    "clicktimestamp_iso8601": "2025-10-23T21:32:08Z",
    "clickcount": 0,
    "clicktrend": 0,
    "ssl_error": 0,
    "geo_lat": null,
    "geo_long": null,
    "geo_distance": null,
    "has_extended_info": false
  },
  {
    "changeuuid": "98bca4ad-da31-4024-b320-0890530634d4",
    "stationuuid": "6108fd19-5cda-4907-afdb-529b373b8df4",
    "serveruuid": "a4f12558-c67e-4a3b-b1ce-f8a157967749",
    "name": "info.m3u8",
    "url": "https://raw.githubusercontent.com/naveenland4/UTLive/main/assets/info.m3u8",
    "url_resolved": "https://raw.githubusercontent.com/naveenland4/UTLive/main/assets/info.m3u8",
    "homepage": "",
    "favicon": "",
    "tags": "",
    "country": "",
    "countrycode": "",
    "iso_3166_2": "",
    "state": "",
    "language": "",
    "languagecodes": "",
    "votes": 0,
    "lastchangetime": "2025-10-23 21:32:08",
    "lastchangetime_iso8601": "2025-10-23T21:32:08Z",
    "codec": "MP3",
    "bitrate": 128,
    "hls": 1,
    "lastcheckok": 1,
    "lastchecktime": "2025-10-23 21:32:08",
    "lastchecktime_iso8601": "2025-10-23T21:32:08Z",
    "lastcheckoktime": "2025-10-23 21:32:08",
    "lastcheckoktime_iso8601": "2025-10-23T21:32:08Z",
    "lastlocalchecktime": "2025-10-23 21:32:08",
    "lastlocalchecktime_iso8601": "2025-10-23T21:32:08Z",
    "clicktimestamp": "2025-10-23 21:32:08",
    "clicktimestamp_iso8601": "2025-10-23T21:32:08Z",
    "clickcount": 0,
    "clicktrend": 0,
    "ssl_error": 0,
    "geo_lat": null,
    "geo_long": null,
    "geo_distance": null,
    "has_extended_info": false
  }
]